simplon
