Metadata-Version: 1.0
Name: simplon.plone.ldap
Version: 1.0
Summary: LDAP control panel for Plone 3
Home-page: http://code.simplon.biz/svn/zope/simplon.plone.ldap
Author: Wichert Akkerman - Simplon
Author-email: wichert@simplon.biz
License: GPL
Keywords: plone ldap
Platform: UNKNOWN
Classifier: Framework :: Plone
Classifier: Framework :: Zope2
Classifier: Programming Language :: Python
Classifier: Topic :: Software Development :: Libraries :: Python Modules
Classifier: Topic :: System :: Systems Administration :: Authentication/Directory :: LDAP
